banyan/__init__.py
banyan/cli.py
banyan/cli_utils.py
banyan/core.py
banyan/example.py
banyan/integrity.py
banyan/sdk.py
banyan/storage.py
banyan_sdk-1.0.1.dist-info/licenses/LICENSE
banyan_sdk-1.0.1.dist-info/METADATA
banyan_sdk-1.0.1.dist-info/WHEEL
banyan_sdk-1.0.1.dist-info/entry_points.txt
banyan_sdk-1.0.1.dist-info/top_level.txt
banyan_sdk-1.0.1.dist-info/RECORD
