Metadata-Version: 2.4
Name: banyan-sdk
Version: 1.0.1
Summary: Python SDK for Banyan (Prompt Stack Manager) - manage, version, and A/B test your LLM prompts
Home-page: https://github.com/yuvvantalreja/banyan-sdk
Author: Banyan Team
Author-email: Banyan Team <support@banyan.dev>
Maintainer-email: Banyan Team <support@banyan.dev>
License: MIT
Project-URL: Homepage, https://github.com/banyan-team/banyan-sdk
Project-URL: Repository, https://github.com/banyan-team/banyan-sdk
Project-URL: Documentation, https://docs.banyan.dev
Project-URL: Bug Reports, https://github.com/banyan-team/banyan-sdk/issues
Project-URL: Changelog, https://github.com/banyan-team/banyan-sdk/blob/main/CHANGELOG.md
Keywords: llm,prompt,logging,ai,machine-learning,openai,anthropic,experiments,a-b-testing,versioning,banyan
Classifier: Development Status :: 4 - Beta
Classifier: Intended Audience :: Developers
Classifier: License :: OSI Approved :: MIT License
Classifier: Operating System :: OS Independent
Classifier: Programming Language :: Python :: 3
Classifier: Programming Language :: Python :: 3.7
Classifier: Programming Language :: Python :: 3.8
Classifier: Programming Language :: Python :: 3.9
Classifier: Programming Language :: Python :: 3.10
Classifier: Programming Language :: Python :: 3.11
Classifier: Programming Language :: Python :: 3.12
Classifier: Topic :: Software Development :: Libraries :: Python Modules
Classifier: Topic :: Internet :: WWW/HTTP :: Dynamic Content
Classifier: Topic :: Scientific/Engineering :: Artificial Intelligence
Requires-Python: >=3.7
License-File: LICENSE
Requires-Dist: requests>=2.25.0
Requires-Dist: typer[all]>=0.9.0
Requires-Dist: rich>=13.0.0
Requires-Dist: pyyaml>=6.0.0
Provides-Extra: dev
Requires-Dist: pytest>=6.0; extra == "dev"
Requires-Dist: pytest-asyncio; extra == "dev"
Requires-Dist: black; extra == "dev"
Requires-Dist: flake8; extra == "dev"
Requires-Dist: mypy; extra == "dev"
Requires-Dist: twine; extra == "dev"
Requires-Dist: build; extra == "dev"
Requires-Dist: pytest-cov; extra == "dev"
Dynamic: author
Dynamic: home-page
Dynamic: license-file
Dynamic: requires-python
